llg3d/__init__.py
llg3d/__main__.py
llg3d/element.py
llg3d/grid.py
llg3d/main.py
llg3d/output.py
llg3d/parameters.py
llg3d/simulation.py
llg3d/post/__init__.py
llg3d/post/plot_results.py
llg3d/post/process.py
llg3d/post/temperature.py
llg3d/solver/__init__.py
llg3d/solver/jax.py
llg3d/solver/mpi.py
llg3d/solver/numpy.py
llg3d/solver/opencl.py
llg3d/solver/solver.py
llg3d-2.0.1.dist-info/licenses/AUTHORS
llg3d-2.0.1.dist-info/licenses/LICENSE
llg3d-2.0.1.dist-info/METADATA
llg3d-2.0.1.dist-info/WHEEL
llg3d-2.0.1.dist-info/entry_points.txt
llg3d-2.0.1.dist-info/top_level.txt
llg3d-2.0.1.dist-info/RECORD
