Metadata-Version: 2.4
Name: llg3d
Version: 2.0.1
Summary: A solver for the stochastic Landau-Lifshitz-Gilbert equation in 3D
Author-email: Clémentine Courtès <clementine.courtes@math.unistra.fr>, Matthieu Boileau <matthieu.boileau@math.unistra.fr>
Project-URL: Homepage, https://gitlab.math.unistra.fr/llg3d/llg3d
Classifier: Programming Language :: Python :: 3
Classifier: License :: OSI Approved :: MIT License
Classifier: Operating System :: OS Independent
Requires-Python: >=3.9
License-File: LICENSE
License-File: AUTHORS
Requires-Dist: numpy
Requires-Dist: matplotlib
Requires-Dist: scipy
Provides-Extra: mpi
Requires-Dist: mpi4py; extra == "mpi"
Provides-Extra: opencl
Requires-Dist: pyopencl; extra == "opencl"
Requires-Dist: mako; extra == "opencl"
Provides-Extra: jax
Requires-Dist: jax[cuda]; sys_platform != "darwin" and extra == "jax"
Requires-Dist: jax[cpu]; sys_platform == "darwin" and extra == "jax"
Dynamic: license-file
